ambush/__init__.py
ambush/_version.py
ambush/tests/__init__.py
ambush/tests/conftest.py
ambush/tests/test_examples.py
ambush-0.0.1.dist-info/AUTHORS.rst
ambush-0.0.1.dist-info/LICENSE
ambush-0.0.1.dist-info/METADATA
ambush-0.0.1.dist-info/WHEEL
ambush-0.0.1.dist-info/entry_points.txt
ambush-0.0.1.dist-info/top_level.txt
ambush-0.0.1.dist-info/RECORD
